boilerdata/__init__.py
boilerdata/axes_enum.py
boilerdata/types.py
boilerdata/validation.py
boilerdata/models/__init__.py
boilerdata/models/axes.py
boilerdata/models/params.py
boilerdata/models/paths.py
boilerdata/stages/__init__.py
boilerdata/stages/axes.py
boilerdata/stages/literature.py
boilerdata/stages/metrics.ipynb
boilerdata/stages/originlab.py
boilerdata/stages/parse_benchmarks.py
boilerdata/stages/pipeline.py
boilerdata/stages/runs.py
boilerdata-2024.1.2.dist-info/LICENSE
boilerdata-2024.1.2.dist-info/WHEEL
boilerdata-2024.1.2.dist-info/METADATA
boilerdata-2024.1.2.dist-info/RECORD
