Metadata-Version: 2.1
Name: boilerdata
Version: 2024.1.2
Summary: Data processing pipeline for a nucleate pool boiling apparatus
Author-email: Blake Naccarato <blake.naccarato@gmail.com>
Requires-Python: >=3.11
Classifier: License :: OSI Approved :: MIT License
Classifier: Programming Language :: Python :: 3.11
Classifier: Programming Language :: Python :: 3.12
Requires-Dist: boilercore>=2024.1.3
Requires-Dist: ipython>=8.25.0
Requires-Dist: matplotlib>=3.8.3
Requires-Dist: numpy>=1.26.4
Requires-Dist: originpro>=1.1.7 ; sys_platform == 'windows'
Requires-Dist: pandas[hdf5,performance]>=2.2.0
Requires-Dist: pandera>=0.18.0
Requires-Dist: propshop>=0.1.3
Requires-Dist: pyarrow>=15.0.0
Requires-Dist: pydantic>=2.6.1
Requires-Dist: pyXSteam>=0.4.9
Requires-Dist: scipy>=1.12.0
Requires-Dist: seaborn>=0.13.2
Project-URL: Changes, https://softboiler.github.io/boilerdata/changelog.html
Project-URL: Docs, https://softboiler.github.io/boilerdata
Project-URL: Home, https://github.com/softboiler/boilerdata
Project-URL: Tracker, https://github.com/softboiler/boilerdata/issues
